{
  "docusaurus-plugin-content-docs": {
    "default": {
      "loadedVersions": [
        {
          "versionName": "current",
          "versionLabel": "Next",
          "versionPath": "/docs",
          "isLast": true,
          "routePriority": -1,
          "sidebarFilePath": "/Users/ilariaventurini/accurat/colors-convert/docs/sidebars.js",
          "docsDirPath": "/Users/ilariaventurini/accurat/colors-convert/docs/docs",
          "mainDocId": "api/api1",
          "sidebars": {
            "documentation": [
              {
                "collapsed": true,
                "type": "category",
                "label": "Example",
                "items": [
                  {
                    "type": "doc",
                    "id": "documentation/documentation1"
                  }
                ]
              }
            ],
            "api": [
              {
                "collapsed": true,
                "type": "category",
                "label": "Color formats",
                "items": [
                  {
                    "type": "doc",
                    "id": "api/api1"
                  }
                ]
              }
            ]
          },
          "permalinkToSidebar": {
            "/docs/": "documentation"
          },
          "docs": [
            {
              "unversionedId": "api/api1",
              "id": "api/api1",
              "isDocsHomePage": false,
              "title": "Api 1",
              "description": "Lorem ipsum dolor sit amet, consectetur adipiscing elit, sed do eiusmod tempor incididunt ut labore et dolore magna aliqua.",
              "source": "@site/docs/api/api1.md",
              "slug": "/",
              "permalink": "/docs/",
              "editUrl": "https://github.com/ilariaventurini/colors-convert/docs/api/api1.md",
              "version": "current",
              "sidebar_label": "Style Guide",
              "sidebar": "api"
            },
            {
              "unversionedId": "doc1",
              "id": "doc1",
              "isDocsHomePage": false,
              "title": "Style Guide",
              "description": "You can write content using GitHub-flavored Markdown syntax.",
              "source": "@site/docs/doc1.md",
              "slug": "/",
              "permalink": "/docs/",
              "editUrl": "https://github.com/ilariaventurini/colors-convert/docs/doc1.md",
              "version": "current",
              "sidebar_label": "Style Guide"
            },
            {
              "unversionedId": "doc2",
              "id": "doc2",
              "isDocsHomePage": false,
              "title": "Document Number 2",
              "description": "This is a link to another document. This is a link to an external page.",
              "source": "@site/docs/doc2.md",
              "slug": "/doc2",
              "permalink": "/docs/doc2",
              "editUrl": "https://github.com/ilariaventurini/colors-convert/docs/doc2.md",
              "version": "current"
            },
            {
              "unversionedId": "doc3",
              "id": "doc3",
              "isDocsHomePage": false,
              "title": "This is Document Number 3",
              "description": "Lorem ipsum dolor sit amet, consectetur adipiscing elit. In ac euismod odio, eu consequat dui. Nullam molestie consectetur risus id imperdiet. Proin sodales ornare turpis, non mollis massa ultricies id. Nam at nibh scelerisque, feugiat ante non, dapibus tortor. Vivamus volutpat diam quis tellus elementum bibendum. Praesent semper gravida velit quis aliquam. Etiam in cursus neque. Nam lectus ligula, malesuada et mauris a, bibendum faucibus mi. Phasellus ut interdum felis. Phasellus in odio pulvinar, porttitor urna eget, fringilla lectus. Aliquam sollicitudin est eros. Mauris consectetur quam vitae mauris interdum hendrerit. Lorem ipsum dolor sit amet, consectetur adipiscing elit.",
              "source": "@site/docs/doc3.md",
              "slug": "/doc3",
              "permalink": "/docs/doc3",
              "editUrl": "https://github.com/ilariaventurini/colors-convert/docs/doc3.md",
              "version": "current"
            },
            {
              "unversionedId": "documentation/documentation1",
              "id": "documentation/documentation1",
              "isDocsHomePage": false,
              "title": "Documentation 1",
              "description": "Lorem ipsum dolor sit amet, consectetur adipiscing elit, sed do eiusmod tempor incididunt ut labore et dolore magna aliqua. Ut enim ad minim veniam, quis nostrud exercitation ullamco laboris nisi ut aliquip ex ea commodo consequat. Duis aute irure dolor in reprehenderit in voluptate velit esse cillum dolore eu fugiat nulla pariatur. Excepteur sint occaecat cupidatat non proident, sunt in culpa qui officia deserunt mollit anim id est laborum. Sed ut perspiciatis unde omnis iste natus error sit voluptatem accusantium doloremque laudantium, totam rem aperiam, eaque ipsa quae ab illo inventore veritatis et quasi architecto beatae vitae dicta sunt explicabo. Nemo enim ipsam voluptatem quia voluptas sit aspernatur aut odit aut fugit, sed quia consequuntur magni dolores eos qui ratione voluptatem sequi nesciunt. Neque porro quisquam est, qui dolorem ipsum quia dolor sit amet, consectetur, adipisci velit, sed quia non numquam eius modi tempora incidunt ut labore et dolore magnam aliquam quaerat voluptatem. Ut enim ad minima veniam, quis nostrum exercitationem ullam corporis suscipit laboriosam, nisi ut aliquid ex ea commodi consequatur? Quis autem vel eum iure reprehenderit qui in ea voluptate velit esse quam nihil molestiae consequatur, vel illum qui dolorem eum fugiat quo voluptas nulla pariatur?",
              "source": "@site/docs/documentation/documentation1.md",
              "slug": "/",
              "permalink": "/docs/",
              "editUrl": "https://github.com/ilariaventurini/colors-convert/docs/documentation/documentation1.md",
              "version": "current",
              "sidebar_label": "Style Guide",
              "sidebar": "documentation"
            },
            {
              "unversionedId": "mdx",
              "id": "mdx",
              "isDocsHomePage": false,
              "title": "Powered by MDX",
              "description": "You can write JSX and use React components within your Markdown thanks to MDX.",
              "source": "@site/docs/mdx.md",
              "slug": "/mdx",
              "permalink": "/docs/mdx",
              "editUrl": "https://github.com/ilariaventurini/colors-convert/docs/mdx.md",
              "version": "current"
            }
          ]
        }
      ]
    }
  },
  "docusaurus-plugin-content-blog": {
    "default": null
  },
  "docusaurus-plugin-content-pages": {
    "default": [
      {
        "type": "jsx",
        "permalink": "/",
        "source": "@site/src/pages/index.js"
      }
    ]
  },
  "docusaurus-plugin-debug": {
    "default": null
  },
  "docusaurus-theme-classic": {
    "default": null
  }
}